LICENSE
shadowsocks/__main__.py
shadowsocks/app.py
shadowsocks/cipherman.py
shadowsocks/ciphers.py
shadowsocks/core.py
shadowsocks/gen/async_protos/aioshadowsocks_grpc.py
shadowsocks/gen/async_protos/aioshadowsocks_pb2.py
shadowsocks/gen/sync_protos/aioshadowsocks_pb2.py
shadowsocks/gen/sync_protos/aioshadowsocks_pb2_grpc.py
shadowsocks/mdb/__init__.py
shadowsocks/mdb/models.py
shadowsocks/metrics.py
shadowsocks/protocol_flag.py
shadowsocks/proxyman.py
shadowsocks/ratelimit.py
shadowsocks/rpc_clients.py
shadowsocks/services.py
shadowsocks/utils.py
aioshadowsocks-0.1.8.dist-info/entry_points.txt
aioshadowsocks-0.1.8.dist-info/LICENSE
aioshadowsocks-0.1.8.dist-info/WHEEL
aioshadowsocks-0.1.8.dist-info/METADATA
aioshadowsocks-0.1.8.dist-info/RECORD
