Metadata-Version: 2.1
Name: aioshadowsocks
Version: 0.1.8
Summary: shadowsocks build with asyncio , also support many user in one port
License: GPLV3
Keywords: shadowsocsk,asyncio,grpc
Author: ehco1996
Author-email: zh19960202@gmail.com
Requires-Python: >=3.8.0,<4.0
Classifier: License :: Other/Proprietary License
Classifier: Programming Language :: Python :: 3
Classifier: Programming Language :: Python :: 3.8
Classifier: Programming Language :: Python :: 3.9
Requires-Dist: aiohttp (==3.7.4)
Requires-Dist: bloom-filter (==1.3)
Requires-Dist: cryptography (>=3.2.1,<4.0.0)
Requires-Dist: fire (==0.4.0)
Requires-Dist: grpcio (>=1.35.0,<2.0.0)
Requires-Dist: grpclib (==0.4.1)
Requires-Dist: hkdf (==0.0.3)
Requires-Dist: httpx (>=0.17.1,<0.18.0)
Requires-Dist: peewee (==3.14.4)
Requires-Dist: prometheus-async (==19.2.0)
Requires-Dist: prometheus-client (==0.10.1)
Requires-Dist: protobuf (==3.13.0)
Requires-Dist: sentry-sdk (==1.0.0)
